rowantree/contracts/__init__.py
rowantree/contracts/dto/__init__.py
rowantree/contracts/dto/base_model.py
rowantree/contracts/dto/action/__init__.py
rowantree/contracts/dto/action/action.py
rowantree/contracts/dto/action/action_queue.py
rowantree/contracts/dto/user/__init__.py
rowantree/contracts/dto/user/event.py
rowantree/contracts/dto/user/feature_state.py
rowantree/contracts/dto/user/income.py
rowantree/contracts/dto/user/notification.py
rowantree/contracts/dto/user/state.py
rowantree/contracts/dto/user/store.py
rowantree/contracts/dto/user/user.py
rowantree/contracts/types/__init__.py
rowantree/contracts/types/feature_detail_type.py
rowantree/contracts/types/feature_type.py
rowantree/contracts/types/income_source_type.py
rowantree/contracts/types/store_type.py
rowantree/contracts/types/user_event_other_type.py
rowantree.contracts-1.0.0.dist-info/LICENSE
rowantree.contracts-1.0.0.dist-info/METADATA
rowantree.contracts-1.0.0.dist-info/WHEEL
rowantree.contracts-1.0.0.dist-info/top_level.txt
rowantree.contracts-1.0.0.dist-info/RECORD
