Metadata-Version: 2.1
Name: rowantree.contracts
Version: 1.0.0
Summary: Rowan Tree Contracts
Author: Joshua C. Burt
Author-email: joshburt@shapeandshare.com
License: MIT
Requires-Python: >=3.9
License-File: LICENSE
Requires-Dist: pydantic (~=1.10)
